marks_averagee/__init__.py
marks_averagee/averagee.py
marks_averagee/setup.py
averagee_calculatorr-1.0.0.dist-info/METADATA
averagee_calculatorr-1.0.0.dist-info/WHEEL
averagee_calculatorr-1.0.0.dist-info/top_level.txt
averagee_calculatorr-1.0.0.dist-info/RECORD
