Metadata-Version: 2.1
Name: averagee_calculatorr
Version: 1.0.0
Summary: A library to calculate the average of marks
Author: Your Name
Requires-Python: >=3.6
